MANIFEST.in
README.md
setup.py
PKGBUILD/budget.desktop
PKGBUILD/budget.svg
PKGBUILD/budget-128/budget.png
PKGBUILD/budget-128/budget.svg
PKGBUILD/budget-16/budget.png
PKGBUILD/budget-16/budget.svg
PKGBUILD/budget-24/budget.png
PKGBUILD/budget-24/budget.svg
PKGBUILD/budget-32/budget.png
PKGBUILD/budget-32/budget.svg
PKGBUILD/budget-48/budget.png
PKGBUILD/budget-48/budget.svg
PKGBUILD/budget-64/budget.png
PKGBUILD/budget-64/budget.svg
budget/__init__.py
budget/add_popover.py
budget/budget.py
budget/calc.py
budget/data.py
budget/edit_mode.py
budget/menu_popover.py
budget/overview.py
budget/projections.py
budget/style.css
budget/transactions.py
budget/window.py
budget.egg-info/PKG-INFO
budget.egg-info/SOURCES.txt
budget.egg-info/dependency_links.txt
budget.egg-info/entry_points.txt
budget.egg-info/top_level.txt